rf_linkbudget/__init__.py
rf_linkbudget/circuit.py
rf_linkbudget/result.py
rf_linkbudget/rfmath.py
rf_linkbudget/verify.py
test/__init__.py
test/circuit.py
test/components.py
test/verifyParameter.py
rf_linkbudget-1.1.7.dist-info/LICENSE
rf_linkbudget-1.1.7.dist-info/METADATA
rf_linkbudget-1.1.7.dist-info/WHEEL
rf_linkbudget-1.1.7.dist-info/top_level.txt
rf_linkbudget-1.1.7.dist-info/RECORD
