Metadata-Version: 2.1
Name: rf-linkbudget
Version: 1.1.7
Summary: A simple rf-linkbudget calculation tool
Home-page: https://github.com/hwengineer/rf_linkbudget
Author: Alexander Ott
Author-email: alexander.ott.ottale@gmail.com
License: MIT
Classifier: Programming Language :: Python :: 3
Classifier: License :: OSI Approved :: MIT License
Classifier: Operating System :: OS Independent
Requires-Python: >=3.6
License-File: LICENSE
